swapcoffee/tokens/__init__.py
swapcoffee/tokens/__meta__.py
swapcoffee/tokens/client.py
swapcoffee/tokens/exceptions.py
swapcoffee/tokens/py.typed
swapcoffee/tokens/methods/__init__.py
swapcoffee/tokens/methods/assign_label.py
swapcoffee/tokens/methods/assign_label_by_address.py
swapcoffee/tokens/methods/assign_label_by_symbol.py
swapcoffee/tokens/methods/base.py
swapcoffee/tokens/methods/create_label.py
swapcoffee/tokens/methods/delete_label.py
swapcoffee/tokens/methods/get_blockhains.py
swapcoffee/tokens/methods/get_labels.py
swapcoffee/tokens/methods/get_token.py
swapcoffee/tokens/methods/get_token_by_address.py
swapcoffee/tokens/methods/get_token_by_symbol.py
swapcoffee/tokens/methods/get_tokens.py
swapcoffee/tokens/methods/get_tokens_by_addresses.py
swapcoffee/tokens/methods/get_tokens_by_symbols.py
swapcoffee/tokens/methods/unbind_label.py
swapcoffee/tokens/methods/unbind_label_by_symbol.py
swapcoffee/tokens/methods/update_label.py
swapcoffee/tokens/types/__init__.py
swapcoffee/tokens/types/base.py
swapcoffee/tokens/types/blockchain.py
swapcoffee/tokens/types/blockchain_token.py
swapcoffee/tokens/types/message.py
swapcoffee/tokens/types/page.py
swapcoffee/tokens/types/staking_pool.py
swapcoffee/tokens/types/token_label.py
swapcoffee/tokens/types/token_label_relation.py
swapcoffee_tokens-1.0.4.dist-info/METADATA
swapcoffee_tokens-1.0.4.dist-info/WHEEL
swapcoffee_tokens-1.0.4.dist-info/licenses/LICENSE
swapcoffee_tokens-1.0.4.dist-info/RECORD
